NathanJamesToolbox/NathanJamesToolbox.py
NathanJamesToolbox-1.3.15.dist-info/LICENSE.txt
NathanJamesToolbox-1.3.15.dist-info/METADATA
NathanJamesToolbox-1.3.15.dist-info/WHEEL
NathanJamesToolbox-1.3.15.dist-info/top_level.txt
NathanJamesToolbox-1.3.15.dist-info/RECORD
