Metadata-Version: 2.1
Name: NathanJamesToolbox
Version: 1.3.15
Summary: Collection of tools developed for NathanJames
Home-page: https://github.com/pfajardo-nj/NathanJamesToolbox
License: MIT
Platform: UNKNOWN
Classifier: License :: OSI Approved :: MIT License
Requires-Dist: requests
Requires-Dist: slacker
Requires-Dist: datetime
Requires-Dist: google.cloud
Requires-Dist: pymysql
Requires-Dist: selenium
